OpenRadio/__init__.py
OpenRadio/assets/OpenRadio.icon
OpenRadio/assets/OpenRadio.png
OpenRadio/assets/icons/alarm-symbolic.svg
OpenRadio/assets/icons/application-exit.png
OpenRadio/assets/icons/applications-internet.png
OpenRadio/assets/icons/dialog-information.png
OpenRadio/assets/icons/emblem-system.png
OpenRadio/assets/icons/globe-symbolic.svg
OpenRadio/assets/icons/go-down-symbolic.svg
OpenRadio/assets/icons/go-previous-symbolic.svg
OpenRadio/assets/icons/go-up-symbolic.svg
OpenRadio/assets/icons/list-add-symbolic.svg
OpenRadio/assets/icons/map-search-outline.png
OpenRadio/assets/icons/media-playback-pause-symbolic.svg
OpenRadio/assets/icons/media-playback-start-symbolic.svg
OpenRadio/assets/icons/media-playback-stop-symbolic.svg
OpenRadio/assets/icons/network-wireless-hotspot-symbolic.svg
OpenRadio/assets/icons/search-web.png
OpenRadio/assets/icons/star-outline.png
OpenRadio/assets/icons/star.png
OpenRadio/assets/icons/tag-search-outline.png
OpenRadio/assets/icons/user-trash-symbolic.svg
OpenRadio/assets/icons/countries/ad.svg
OpenRadio/assets/icons/countries/ae.svg
OpenRadio/assets/icons/countries/af.svg
OpenRadio/assets/icons/countries/ag.svg
OpenRadio/assets/icons/countries/ai.svg
OpenRadio/assets/icons/countries/al.svg
OpenRadio/assets/icons/countries/am.svg
OpenRadio/assets/icons/countries/ao.svg
OpenRadio/assets/icons/countries/aq.svg
OpenRadio/assets/icons/countries/ar.svg
OpenRadio/assets/icons/countries/as.svg
OpenRadio/assets/icons/countries/at.svg
OpenRadio/assets/icons/countries/au.svg
OpenRadio/assets/icons/countries/aw.svg
OpenRadio/assets/icons/countries/ax.svg
OpenRadio/assets/icons/countries/az.svg
OpenRadio/assets/icons/countries/ba.svg
OpenRadio/assets/icons/countries/bb.svg
OpenRadio/assets/icons/countries/bd.svg
OpenRadio/assets/icons/countries/be.svg
OpenRadio/assets/icons/countries/bf.svg
OpenRadio/assets/icons/countries/bg.svg
OpenRadio/assets/icons/countries/bh.svg
OpenRadio/assets/icons/countries/bi.svg
OpenRadio-1.1.2.dist-info/LICENSE.md
OpenRadio-1.1.2.dist-info/LICENSE_Flags.md
OpenRadio-1.1.2.dist-info/LICENSE_Icons.md
OpenRadio-1.1.2.dist-info/METADATA
OpenRadio-1.1.2.dist-info/WHEEL
OpenRadio-1.1.2.dist-info/entry_points.txt
OpenRadio-1.1.2.dist-info/top_level.txt
OpenRadio-1.1.2.dist-info/RECORD
